{"kind":"identitytoolkit#DownloadAccountResponse","users":[{"localId":"0CP479xFPzUVbdhQ2PGe5MyTrIip","createdAt":"1755842951627","lastLoginAt":"1755842951627","displayName":"小林 大輔","passwordHash":"fakeHash:salt=fakeSalttAmJkJgNOE7VHL5AT3zq:password=UtGJspRz","salt":"fakeSalttAmJkJgNOE7VHL5AT3zq","passwordUpdatedAt":1755928332765,"providerUserInfo":[{"providerId":"password","email":"student019@example.com","federatedId":"student019@example.com","rawId":"student019@example.com","displayName":"小林 大輔"}],"validSince":"1755928332","email":"student019@example.com","emailVerified":false,"disabled":false},{"localId":"0rKJYRg7zghnxZXe18P4fF1h9SB7","createdAt":"1755842951593","lastLoginAt":"1755842951593","displayName":"小林 大輔","passwordHash":"fakeHash:salt=fakeSaltGu10NUAiGwByQ9KIxQMI:password=t3vqA7mp","salt":"fakeSaltGu10NUAiGwByQ9KIxQMI","passwordUpdatedAt":1755928332765,"providerUserInfo":[{"providerId":"password","email":"student099@example.com","federatedId":"student099@example.com","rawId":"student099@example.com","displayName":"小林 大輔"}],"validSince":"1755928332","email":"student099@example.com","emailVerified":false,"disabled":false},{"localId":"1QbLGYuy07f2vPflphfPReOwMiNB","createdAt":"1755842951653","lastLoginAt":"1755842951653","displayName":"佐藤 太郎","passwordHash":"fakeHash:salt=fakeSaltArdOhMYGgFLtMTfALM7E:password=FvN1Bcpn","salt":"fakeSaltArdOhMYGgFLtMTfALM7E","passwordUpdatedAt":1755928332765,"providerUserInfo":[{"providerId":"password","email":"student041@example.com","federatedId":"student041@example.com","rawId":"student041@example.com","displayName":"佐藤 太郎"}],"validSince":"1755928332","email":"student041@example.com","emailVerified":false,"disabled":false},{"localId":"1R14dK206fEayryGFDQb4EmBxYCQ","createdAt":"1755842951730","lastLoginAt":"1755842951730","displayName":"鈴木 花子","passwordHash":"fakeHash:salt=fakeSaltipyy5acns0f1ahsR4Q3x:password=67VlTUt6","salt":"fakeSaltipyy5acns0f1ahsR4Q3x","passwordUpdatedAt":1755928332765,"providerUserInfo":[{"providerId":"password","email":"student002@example.com","federatedId":"student002@example.com","rawId":"student002@example.com","displayName":"鈴木 花子"}],"validSince":"1755928332","email":"student002@example.com","emailVerified":false,"disabled":false},{"localId":"25DdqDXkVtGSKyWDnAQc34b6mseP","createdAt":"1755842951719","lastLoginAt":"1755842951719","displayName":"伊藤 健","passwordHash":"fakeHash:salt=fakeSaltf59umYiiG3tMxEXsIegx:password=Yb6Gq8ER","salt":"fakeSaltf59umYiiG3tMxEXsIegx","passwordUpdatedAt":1755928332765,"providerUserInfo":[{"providerId":"password","email":"student075@example.com","federatedId":"student075@example.com","rawId":"student075@example.com","displayName":"伊藤 健"}],"validSince":"1755928332","email":"student075@example.com","emailVerified":false,"disabled":false},{"localId":"31f8CR4FdO4H4lHRWaZsYmnroXqg","createdAt":"1755842951615","lastLoginAt":"1755842951615","displayName":"渡辺 彩香","passwordHash":"fakeHash:salt=fakeSaltsCpCuI6Dxt3zZszUSoXM:password=VUvDb3sC","salt":"fakeSaltsCpCuI6Dxt3zZszUSoXM","passwordUpdatedAt":1755928332766,"providerUserInfo":[{"providerId":"password","email":"student016@example.com","federatedId":"student016@example.com","rawId":"student016@example.com","displayName":"渡辺 彩香"}],"validSince":"1755928332","email":"student016@example.com","emailVerified":false,"disabled":false},{"localId":"3vv9AXyduy4a6BZXq2Sa0DWO576O","createdAt":"1755602842117","lastLoginAt":"1755828094540","displayName":"私立EduSupport高校","photoUrl":"","passwordHash":"fakeHash:salt=fakeSaltxVs0CZ1B7RgOB7VMG6Yr:password=19751975","salt":"fakeSaltxVs0CZ1B7RgOB7VMG6Yr","passwordUpdatedAt":1755928332766,"providerUserInfo":[{"providerId":"password","email":"ststt@tst.com","federatedId":"ststt@tst.com","rawId":"ststt@tst.com","displayName":"私立EduSupport高校","photoUrl":""}],"validSince":"1755928332","email":"ststt@tst.com","emailVerified":false,"disabled":false},{"localId":"4taeYBEnUSK1MfVZvXUSs60xvoRG","createdAt":"1755842951726","lastLoginAt":"1755842951726","displayName":"山本 翔","passwordHash":"fakeHash:salt=fakeSaltomOd6ITZP3TbjiWb5GUn:password=gzhz22Zh","salt":"fakeSaltomOd6ITZP3TbjiWb5GUn","passwordUpdatedAt":1755928332766,"providerUserInfo":[{"providerId":"password","email":"student017@example.com","federatedId":"student017@example.com","rawId":"student017@example.com","displayName":"山本 翔"}],"validSince":"1755928332","email":"student017@example.com","emailVerified":false,"disabled":false},{"localId":"5FC433Z3xefIHLYhAWKZTa75Y0aR","createdAt":"1755842951738","lastLoginAt":"1755842951738","displayName":"山本 翔","passwordHash":"fakeHash:salt=fakeSaltyYghFzeJZiG7qJOk4WRP:password=8QAZD6Wy","salt":"fakeSaltyYghFzeJZiG7qJOk4WRP","passwordUpdatedAt":1755928332766,"providerUserInfo":[{"providerId":"password","email":"student087@example.com","federatedId":"student087@example.com","rawId":"student087@example.com","displayName":"山本 翔"}],"validSince":"1755928332","email":"student087@example.com","emailVerified":false,"disabled":false},{"localId":"5mU0F79IhFgICKd4CFGgLf0mhL4X","createdAt":"1755842951515","lastLoginAt":"1755842951515","displayName":"田中 一郎","passwordHash":"fakeHash:salt=fakeSaltIpW9V8R5H2ZD6mqy4L56:password=Cx12TzTM","salt":"fakeSaltIpW9V8R5H2ZD6mqy4L56","passwordUpdatedAt":1755928332766,"providerUserInfo":[{"providerId":"password","email":"student043@example.com","federatedId":"student043@example.com","rawId":"student043@example.com","displayName":"田中 一郎"}],"validSince":"1755928332","email":"student043@example.com","emailVerified":false,"disabled":false},{"localId":"7kFoFIBaExhwRYxProSlRzk6z5FC","createdAt":"1755842951596","lastLoginAt":"1755842951596","displayName":"山本 翔","passwordHash":"fakeHash:salt=fakeSaltEE1uIu4lE3JEDdsBzkXM:password=NPqi7tH9","salt":"fakeSaltEE1uIu4lE3JEDdsBzkXM","passwordUpdatedAt":1755928332766,"providerUserInfo":[{"providerId":"password","email":"student027@example.com","federatedId":"student027@example.com","rawId":"student027@example.com","displayName":"山本 翔"}],"validSince":"1755928332","email":"student027@example.com","emailVerified":false,"disabled":false},{"localId":"9IPqVWecqueSAy9feQLsqOhMjE7e","createdAt":"1755767029263","lastLoginAt":"1755767029263","displayName":"test 管理者","validSince":"1755928332","email":"test@admin.com","emailVerified":false,"disabled":false},{"localId":"9pdCtTNcV5r52IOWHcTFJOXmvX1s","createdAt":"1755842951772","lastLoginAt":"1755842951772","displayName":"高橋 真美","passwordHash":"fakeHash:salt=fakeSaltnroOk9oBELEUd7aQp1UY:password=ze5xpRDs","salt":"fakeSaltnroOk9oBELEUd7aQp1UY","passwordUpdatedAt":1755928332766,"providerUserInfo":[{"providerId":"password","email":"student014@example.com","federatedId":"student014@example.com","rawId":"student014@example.com","displayName":"高橋 真美"}],"validSince":"1755928332","email":"student014@example.com","emailVerified":false,"disabled":false},{"localId":"AZaJk3X5zDZFgC0VBCJmOGR3zULr","createdAt":"1755842951555","lastLoginAt":"1755842951555","displayName":"渡辺 彩香","passwordHash":"fakeHash:salt=fakeSalthwnElZQTxW1sAf5HbwvZ:password=Dyz5awdW","salt":"fakeSalthwnElZQTxW1sAf5HbwvZ","passwordUpdatedAt":1755928332766,"providerUserInfo":[{"providerId":"password","email":"student026@example.com","federatedId":"student026@example.com","rawId":"student026@example.com","displayName":"渡辺 彩香"}],"validSince":"1755928332","email":"student026@example.com","emailVerified":false,"disabled":false},{"localId":"Ag7ij46cpzpoKpIwv1zOIyNID7iu","createdAt":"1755773061146","lastLoginAt":"1755773061146","displayName":"テスト　花子","passwordHash":"fakeHash:salt=fakeSaltigyz3DbwQBbZW36zHdTN:password=nRzM7caF","salt":"fakeSaltigyz3DbwQBbZW36zHdTN","passwordUpdatedAt":1755928332766,"providerUserInfo":[{"providerId":"password","email":"testhanako@example.com","federatedId":"testhanako@example.com","rawId":"testhanako@example.com","displayName":"テスト　花子"}],"validSince":"1755928332","email":"testhanako@example.com","emailVerified":false,"disabled":true},{"localId":"B1ozSMv2KrdNXbNLFbUEoz2qwPE1","createdAt":"1755842951681","lastLoginAt":"1755842951681","displayName":"加藤 結衣","passwordHash":"fakeHash:salt=fakeSaltpa5smBUKpchEH47C75s3:password=keFwlGUK","salt":"fakeSaltpa5smBUKpchEH47C75s3","passwordUpdatedAt":1755928332766,"providerUserInfo":[{"providerId":"password","email":"student020@example.com","federatedId":"student020@example.com","rawId":"student020@example.com","displayName":"加藤 結衣"}],"validSince":"1755928332","email":"student020@example.com","emailVerified":false,"disabled":false},{"localId":"B9IOZMuteclL9Zxd5u7c6GKMSOJk","createdAt":"1755842951757","lastLoginAt":"1755842951757","displayName":"佐藤 太郎","passwordHash":"fakeHash:salt=fakeSaltyFptJmNt4zQZkvBeajUh:password=aKhpEHSa","salt":"fakeSaltyFptJmNt4zQZkvBeajUh","passwordUpdatedAt":1755928332766,"providerUserInfo":[{"providerId":"password","email":"student031@example.com","federatedId":"student031@example.com","rawId":"student031@example.com","displayName":"佐藤 太郎"}],"validSince":"1755928332","email":"student031@example.com","emailVerified":false,"disabled":false},{"localId":"BFE6hKlsyU2EMcfEpHXk55ApulPO","createdAt":"1755842951663","lastLoginAt":"1755842951663","displayName":"加藤 結衣","passwordHash":"fakeHash:salt=fakeSaltks08WA73SKtLP2dCdBbk:password=ZVSHNLRp","salt":"fakeSaltks08WA73SKtLP2dCdBbk","passwordUpdatedAt":1755928332766,"providerUserInfo":[{"providerId":"password","email":"student090@example.com","federatedId":"student090@example.com","rawId":"student090@example.com","displayName":"加藤 結衣"}],"validSince":"1755928332","email":"student090@example.com","emailVerified":false,"disabled":false},{"localId":"BieSgvqLFF1rPoZe8TwV43n5SPET","createdAt":"1755842951641","lastLoginAt":"1755842951641","displayName":"山本 翔","passwordHash":"fakeHash:salt=fakeSaltkk2r0os3qfi8GHXZ5w0T:password=YfvfF63M","salt":"fakeSaltkk2r0os3qfi8GHXZ5w0T","passwordUpdatedAt":1755928332766,"providerUserInfo":[{"providerId":"password","email":"student057@example.com","federatedId":"student057@example.com","rawId":"student057@example.com","displayName":"山本 翔"}],"validSince":"1755928332","email":"student057@example.com","emailVerified":false,"disabled":false},{"localId":"C0b4ol7h3bvn15K1Irtq6NeZHIt8","createdAt":"1755842951521","lastLoginAt":"1755842951521","displayName":"伊藤 健","passwordHash":"fakeHash:salt=fakeSaltorgv5VASuyKSfhZIhki2:password=UWPJfKgo","salt":"fakeSaltorgv5VASuyKSfhZIhki2","passwordUpdatedAt":1755928332766,"providerUserInfo":[{"providerId":"password","email":"student025@example.com","federatedId":"student025@example.com","rawId":"student025@example.com","displayName":"伊藤 健"}],"validSince":"1755928332","email":"student025@example.com","emailVerified":false,"disabled":false},{"localId":"CJR0ptmzOwnvN7EBzz7joTkeVABO","createdAt":"1755842951755","lastLoginAt":"1755842951755","displayName":"鈴木 花子","passwordHash":"fakeHash:salt=fakeSaltpIbDreLwQsiFZU6GRnDN:password=XD6vsmEW","salt":"fakeSaltpIbDreLwQsiFZU6GRnDN","passwordUpdatedAt":1755928332766,"providerUserInfo":[{"providerId":"password","email":"student072@example.com","federatedId":"student072@example.com","rawId":"student072@example.com","displayName":"鈴木 花子"}],"validSince":"1755928332","email":"student072@example.com","emailVerified":false,"disabled":false},{"localId":"CWuPvKGf2M7TS6I1mdlwQI95gSig","createdAt":"1755842951689","lastLoginAt":"1755842951689","displayName":"小林 大輔","passwordHash":"fakeHash:salt=fakeSaltESC25PwKGSMTWyg7mikI:password=91H59WWl","salt":"fakeSaltESC25PwKGSMTWyg7mikI","passwordUpdatedAt":1755928332766,"providerUserInfo":[{"providerId":"password","email":"student079@example.com","federatedId":"student079@example.com","rawId":"student079@example.com","displayName":"小林 大輔"}],"validSince":"1755928332","email":"student079@example.com","emailVerified":false,"disabled":false},{"localId":"Eq9tfIJOUnNh6hZjshAm5uhYN4ht","createdAt":"1755773061144","lastLoginAt":"1755773061144","displayName":"金谷","passwordHash":"fakeHash:salt=fakeSalt8bCLvragoMywSi5mEg98:password=dPKz85Li","salt":"fakeSalt8bCLvragoMywSi5mEg98","passwordUpdatedAt":1755928332766,"providerUserInfo":[{"providerId":"password","email":"testewige.liebe.yt@gmail.com","federatedId":"testewige.liebe.yt@gmail.com","rawId":"testewige.liebe.yt@gmail.com","displayName":"金谷"}],"validSince":"1755928332","email":"testewige.liebe.yt@gmail.com","emailVerified":false,"disabled":false},{"localId":"FQAaVb3KnRcGci2XunmFFShUkCzp","createdAt":"1755843039595","lastLoginAt":"1755843134326","displayName":"公立EduSupport高校 管理者","photoUrl":"","passwordHash":"fakeHash:salt=fakeSaltKqptIWb1plwxkAjep1Ro:password=12345678","salt":"fakeSaltKqptIWb1plwxkAjep1Ro","passwordUpdatedAt":1755928332766,"providerUserInfo":[{"providerId":"password","email":"edusupport@sample.com","federatedId":"edusupport@sample.com","rawId":"edusupport@sample.com","displayName":"公立EduSupport高校 管理者","photoUrl":""}],"validSince":"1755928332","email":"edusupport@sample.com","emailVerified":false,"disabled":false},{"localId":"GIEuZcWCqSGbSXf8b2Ppvc8Zklzi","createdAt":"1755842951672","lastLoginAt":"1755842951672","displayName":"伊藤 健","passwordHash":"fakeHash:salt=fakeSaltQg1JPU9Uw4aXQiKRQi3c:password=oX5CFs1t","salt":"fakeSaltQg1JPU9Uw4aXQiKRQi3c","passwordUpdatedAt":1755928332766,"providerUserInfo":[{"providerId":"password","email":"student005@example.com","federatedId":"student005@example.com","rawId":"student005@example.com","displayName":"伊藤 健"}],"validSince":"1755928332","email":"student005@example.com","emailVerified":false,"disabled":false},{"localId":"GS8jWWMrqlsqnkRBxBpnqDKPK1WK","createdAt":"1755842951713","lastLoginAt":"1755842951713","displayName":"渡辺 彩香","passwordHash":"fakeHash:salt=fakeSalt6xZ9j0VIIBp55SaPWOw5:password=8sg9REhL","salt":"fakeSalt6xZ9j0VIIBp55SaPWOw5","passwordUpdatedAt":1755928332766,"providerUserInfo":[{"providerId":"password","email":"student056@example.com","federatedId":"student056@example.com","rawId":"student056@example.com","displayName":"渡辺 彩香"}],"validSince":"1755928332","email":"student056@example.com","emailVerified":false,"disabled":false},{"localId":"GT1FGrbMVLtLmuGpN6tddXRsJvxq","createdAt":"1755842951583","lastLoginAt":"1755842951583","displayName":"加藤 結衣","passwordHash":"fakeHash:salt=fakeSaltueE1P0uxmI5O5Iplk2B3:password=WrIYjO4K","salt":"fakeSaltueE1P0uxmI5O5Iplk2B3","passwordUpdatedAt":1755928332766,"providerUserInfo":[{"providerId":"password","email":"student030@example.com","federatedId":"student030@example.com","rawId":"student030@example.com","displayName":"加藤 結衣"}],"validSince":"1755928332","email":"student030@example.com","emailVerified":false,"disabled":false},{"localId":"HoJZ3j5r5306qwxP6affAkiwd3Ac","createdAt":"1755842951496","lastLoginAt":"1755842951496","displayName":"田中 一郎","passwordHash":"fakeHash:salt=fakeSaltNu7n2wL6y7P4TSTYGgHA:password=zD4xb3Ul","salt":"fakeSaltNu7n2wL6y7P4TSTYGgHA","passwordUpdatedAt":1755928332766,"providerUserInfo":[{"providerId":"password","email":"student083@example.com","federatedId":"student083@example.com","rawId":"student083@example.com","displayName":"田中 一郎"}],"validSince":"1755928332","email":"student083@example.com","emailVerified":false,"disabled":false},{"localId":"IRciVzvaVwmoF0hAxGFnh7KzOh5B","createdAt":"1755842951590","lastLoginAt":"1755842951590","displayName":"鈴木 花子","passwordHash":"fakeHash:salt=fakeSalt51B2xd5rLbAFhG4UBMoM:password=yTn83wDo","salt":"fakeSalt51B2xd5rLbAFhG4UBMoM","passwordUpdatedAt":1755928332766,"providerUserInfo":[{"providerId":"password","email":"student082@example.com","federatedId":"student082@example.com","rawId":"student082@example.com","displayName":"鈴木 花子"}],"validSince":"1755928332","email":"student082@example.com","emailVerified":false,"disabled":false},{"localId":"JccGYckeKKXULooFaLqcUujueG0O","createdAt":"1755842951717","lastLoginAt":"1755842951717","displayName":"田中 一郎","passwordHash":"fakeHash:salt=fakeSaltpzG2jDS6H5Vh9flOc1ZH:password=sVsBxEvP","salt":"fakeSaltpzG2jDS6H5Vh9flOc1ZH","passwordUpdatedAt":1755928332766,"providerUserInfo":[{"providerId":"password","email":"student093@example.com","federatedId":"student093@example.com","rawId":"student093@example.com","displayName":"田中 一郎"}],"validSince":"1755928332","email":"student093@example.com","emailVerified":false,"disabled":false},{"localId":"LMZqkuhVE5PZgodBtd88m0QWYMJq","createdAt":"1755842951759","lastLoginAt":"1755842951759","displayName":"田中 一郎","passwordHash":"fakeHash:salt=fakeSaltzGO25lTGzARxds0CcdLv:password=JsLLT5zJ","salt":"fakeSaltzGO25lTGzARxds0CcdLv","passwordUpdatedAt":1755928332766,"providerUserInfo":[{"providerId":"password","email":"student053@example.com","federatedId":"student053@example.com","rawId":"student053@example.com","displayName":"田中 一郎"}],"validSince":"1755928332","email":"student053@example.com","emailVerified":false,"disabled":false},{"localId":"Li5mw40cChIusgtLtXeTNQJam3RQ","createdAt":"1755842951567","lastLoginAt":"1755842951567","displayName":"伊藤 健","passwordHash":"fakeHash:salt=fakeSaltQd9JD3acInxcNQCfdQZ8:password=tDTfXpAw","salt":"fakeSaltQd9JD3acInxcNQCfdQZ8","passwordUpdatedAt":1755928332766,"providerUserInfo":[{"providerId":"password","email":"student015@example.com","federatedId":"student015@example.com","rawId":"student015@example.com","displayName":"伊藤 健"}],"validSince":"1755928332","email":"student015@example.com","emailVerified":false,"disabled":false},{"localId":"MPTRElDOK1Tye90nc34ikokf1Ov8","createdAt":"1755842951722","lastLoginAt":"1755842951722","displayName":"佐藤 太郎","passwordHash":"fakeHash:salt=fakeSaltDRRIIHNOeRKwAW0yj95v:password=mmrXTsbo","salt":"fakeSaltDRRIIHNOeRKwAW0yj95v","passwordUpdatedAt":1755928332766,"providerUserInfo":[{"providerId":"password","email":"student061@example.com","federatedId":"student061@example.com","rawId":"student061@example.com","displayName":"佐藤 太郎"}],"validSince":"1755928332","email":"student061@example.com","emailVerified":false,"disabled":false},{"localId":"OJ1Q9DtIFrj5IwgwOiy1AZBegi4T","createdAt":"1755842951665","lastLoginAt":"1755842951665","displayName":"渡辺 彩香","passwordHash":"fakeHash:salt=fakeSaltlnVjPTUAPwNvKCOqhjsJ:password=wie1FyGi","salt":"fakeSaltlnVjPTUAPwNvKCOqhjsJ","passwordUpdatedAt":1755928332766,"providerUserInfo":[{"providerId":"password","email":"student066@example.com","federatedId":"student066@example.com","rawId":"student066@example.com","displayName":"渡辺 彩香"}],"validSince":"1755928332","email":"student066@example.com","emailVerified":false,"disabled":false},{"localId":"PACsemQsWXQxt1dwPW9BdHmc10lj","createdAt":"1755842951648","lastLoginAt":"1755842951648","displayName":"鈴木 花子","passwordHash":"fakeHash:salt=fakeSalthegXkmxFdLjB13CptSO3:password=1h0st40L","salt":"fakeSalthegXkmxFdLjB13CptSO3","passwordUpdatedAt":1755928332766,"providerUserInfo":[{"providerId":"password","email":"student052@example.com","federatedId":"student052@example.com","rawId":"student052@example.com","displayName":"鈴木 花子"}],"validSince":"1755928332","email":"student052@example.com","emailVerified":false,"disabled":false},{"localId":"PIb0kgFLNnVGFnDbUCIU7kEVTiXs","createdAt":"1755842951746","lastLoginAt":"1755842951746","displayName":"中村 美咲","passwordHash":"fakeHash:salt=fakeSaltIdFf7dow2msinxu7SaCI:password=lgtwiDPB","salt":"fakeSaltIdFf7dow2msinxu7SaCI","passwordUpdatedAt":1755928332766,"providerUserInfo":[{"providerId":"password","email":"student078@example.com","federatedId":"student078@example.com","rawId":"student078@example.com","displayName":"中村 美咲"}],"validSince":"1755928332","email":"student078@example.com","emailVerified":false,"disabled":false},{"localId":"PLZghjOdgatS1rIIDG3KASgK3pMC","createdAt":"1755842951509","lastLoginAt":"1755842951509","displayName":"鈴木 花子","passwordHash":"fakeHash:salt=fakeSaltafdsTkD2BALtXhbbQJUo:password=rgjQ1hTH","salt":"fakeSaltafdsTkD2BALtXhbbQJUo","passwordUpdatedAt":1755928332766,"providerUserInfo":[{"providerId":"password","email":"student092@example.com","federatedId":"student092@example.com","rawId":"student092@example.com","displayName":"鈴木 花子"}],"validSince":"1755928332","email":"student092@example.com","emailVerified":false,"disabled":false},{"localId":"PQtX6xfv7UX2GU9T6T6B1QCTN7eb","createdAt":"1755842951621","lastLoginAt":"1755842951621","displayName":"高橋 真美","passwordHash":"fakeHash:salt=fakeSaltaPcvcpLpcqg0LfsDCiLR:password=mWU7cj2M","salt":"fakeSaltaPcvcpLpcqg0LfsDCiLR","passwordUpdatedAt":1755928332766,"providerUserInfo":[{"providerId":"password","email":"student074@example.com","federatedId":"student074@example.com","rawId":"student074@example.com","displayName":"高橋 真美"}],"validSince":"1755928332","email":"student074@example.com","emailVerified":false,"disabled":false},{"localId":"Pok3bQDSRmPCPTd1jiOeUBZn07pS","createdAt":"1755842951765","lastLoginAt":"1755842951765","displayName":"佐藤 太郎","passwordHash":"fakeHash:salt=fakeSalthOBLMuEn2WvPqbvPxxRP:password=PHG2Gyp7","salt":"fakeSalthOBLMuEn2WvPqbvPxxRP","passwordUpdatedAt":1755928332766,"providerUserInfo":[{"providerId":"password","email":"student011@example.com","federatedId":"student011@example.com","rawId":"student011@example.com","displayName":"佐藤 太郎"}],"validSince":"1755928332","email":"student011@example.com","emailVerified":false,"disabled":false},{"localId":"Pubc4joZ8KaFpRWEyIF7s47bu4yo","createdAt":"1755842951775","lastLoginAt":"1755842951775","displayName":"山本 翔","passwordHash":"fakeHash:salt=fakeSalt0IG30pDXLT3WG16l1OR6:password=gfz8PKsH","salt":"fakeSalt0IG30pDXLT3WG16l1OR6","passwordUpdatedAt":1755928332766,"providerUserInfo":[{"providerId":"password","email":"student037@example.com","federatedId":"student037@example.com","rawId":"student037@example.com","displayName":"山本 翔"}],"validSince":"1755928332","email":"student037@example.com","emailVerified":false,"disabled":false},{"localId":"QiKef4cL1pS0E1JJbAio2jxNIdOO","createdAt":"1755842951714","lastLoginAt":"1755842951714","displayName":"佐藤 太郎","passwordHash":"fakeHash:salt=fakeSaltvgtmK8uGMsdlXRVVuvTv:password=wJ7LVoGV","salt":"fakeSaltvgtmK8uGMsdlXRVVuvTv","passwordUpdatedAt":1755928332766,"providerUserInfo":[{"providerId":"password","email":"student001@example.com","federatedId":"student001@example.com","rawId":"student001@example.com","displayName":"佐藤 太郎"}],"validSince":"1755928332","email":"student001@example.com","emailVerified":false,"disabled":false},{"localId":"SOTjp8edpgCUs60q73JpFRgQyg9N","createdAt":"1755842951639","lastLoginAt":"1755842951639","displayName":"山本 翔","passwordHash":"fakeHash:salt=fakeSaltP1SsCZ45N1KWUFqXjPkK:password=gfJMmskp","salt":"fakeSaltP1SsCZ45N1KWUFqXjPkK","passwordUpdatedAt":1755928332766,"providerUserInfo":[{"providerId":"password","email":"student097@example.com","federatedId":"student097@example.com","rawId":"student097@example.com","displayName":"山本 翔"}],"validSince":"1755928332","email":"student097@example.com","emailVerified":false,"disabled":false},{"localId":"T8tGP9iIsXghDmhqYBSm3RsS1Bdv","createdAt":"1755592112411","lastLoginAt":"1755592112411","displayName":"テスト　花子","validSince":"1755928332","email":"hanako@example.com","emailVerified":false,"disabled":false},{"localId":"TH1OnVhxVUwg8lsHAriI8m5zVOwe","createdAt":"1755842951637","lastLoginAt":"1755842951637","displayName":"加藤 結衣","passwordHash":"fakeHash:salt=fakeSaltaLXCApZSFXzdlywQJRmy:password=AGvwrx7E","salt":"fakeSaltaLXCApZSFXzdlywQJRmy","passwordUpdatedAt":1755928332766,"providerUserInfo":[{"providerId":"password","email":"student050@example.com","federatedId":"student050@example.com","rawId":"student050@example.com","displayName":"加藤 結衣"}],"validSince":"1755928332","email":"student050@example.com","emailVerified":false,"disabled":false},{"localId":"UNhdxJtfUfpE8iLFeE2gSCn3lRnv","createdAt":"1755842951617","lastLoginAt":"1755842951617","displayName":"渡辺 彩香","passwordHash":"fakeHash:salt=fakeSaltCy9kj9WNgOgY3VmEYIaV:password=JsiCWOsn","salt":"fakeSaltCy9kj9WNgOgY3VmEYIaV","passwordUpdatedAt":1755928332766,"providerUserInfo":[{"providerId":"password","email":"student096@example.com","federatedId":"student096@example.com","rawId":"student096@example.com","displayName":"渡辺 彩香"}],"validSince":"1755928332","email":"student096@example.com","emailVerified":false,"disabled":false},{"localId":"UktyiEgu74ZdUl0m1vl59C9ALlxM","createdAt":"1755842951645","lastLoginAt":"1755842951645","displayName":"渡辺 彩香","passwordHash":"fakeHash:salt=fakeSaltj1zR4pUTGlBnjxW2HTjP:password=WmJX4P1V","salt":"fakeSaltj1zR4pUTGlBnjxW2HTjP","passwordUpdatedAt":1755928332766,"providerUserInfo":[{"providerId":"password","email":"student006@example.com","federatedId":"student006@example.com","rawId":"student006@example.com","displayName":"渡辺 彩香"}],"validSince":"1755928332","email":"student006@example.com","emailVerified":false,"disabled":false},{"localId":"VB4iVPRQeJO6KV6BKYvxhG1L6wii","createdAt":"1755842951604","lastLoginAt":"1755842951604","displayName":"高橋 真美","passwordHash":"fakeHash:salt=fakeSaltOWEosAtYwA4KdUlJmqvU:password=88g54FKg","salt":"fakeSaltOWEosAtYwA4KdUlJmqvU","passwordUpdatedAt":1755928332766,"providerUserInfo":[{"providerId":"password","email":"student024@example.com","federatedId":"student024@example.com","rawId":"student024@example.com","displayName":"高橋 真美"}],"validSince":"1755928332","email":"student024@example.com","emailVerified":false,"disabled":false},{"localId":"VLxxIpawcdIUMWfJdvlOk10pdbaR","createdAt":"1755842951736","lastLoginAt":"1755842951736","displayName":"小林 大輔","passwordHash":"fakeHash:salt=fakeSalttrtp1ogUjfIexnO0Oayx:password=UyyI5HcJ","salt":"fakeSalttrtp1ogUjfIexnO0Oayx","passwordUpdatedAt":1755928332766,"providerUserInfo":[{"providerId":"password","email":"student009@example.com","federatedId":"student009@example.com","rawId":"student009@example.com","displayName":"小林 大輔"}],"validSince":"1755928332","email":"student009@example.com","emailVerified":false,"disabled":false},{"localId":"VvhzBFOpXHct8SeOcgLKOlhzBbfT","createdAt":"1755842951562","lastLoginAt":"1755842951562","displayName":"中村 美咲","passwordHash":"fakeHash:salt=fakeSaltlE96P1x9SG6tOeXNYolt:password=e4hA3xlW","salt":"fakeSaltlE96P1x9SG6tOeXNYolt","passwordUpdatedAt":1755928332766,"providerUserInfo":[{"providerId":"password","email":"student018@example.com","federatedId":"student018@example.com","rawId":"student018@example.com","displayName":"中村 美咲"}],"validSince":"1755928332","email":"student018@example.com","emailVerified":false,"disabled":false},{"localId":"WIHW4D9teT4EHJKgDpnz6JgRhdc9","createdAt":"1755842951540","lastLoginAt":"1755842951540","displayName":"佐藤 太郎","passwordHash":"fakeHash:salt=fakeSaltGwflW53qtZQD4XehTrh9:password=CCRtWiIf","salt":"fakeSaltGwflW53qtZQD4XehTrh9","passwordUpdatedAt":1755928332766,"providerUserInfo":[{"providerId":"password","email":"student091@example.com","federatedId":"student091@example.com","rawId":"student091@example.com","displayName":"佐藤 太郎"}],"validSince":"1755928332","email":"student091@example.com","emailVerified":false,"disabled":false},{"localId":"WxO1AVwZBKcZXBoYcA5bOTzLl7Zl","createdAt":"1755512402386","lastLoginAt":"1755845691720","displayName":"管理者","photoUrl":"","passwordHash":"fakeHash:salt=fakeSaltlqln0RmO9dp7qN4AgwIK:password=19751975","salt":"fakeSaltlqln0RmO9dp7qN4AgwIK","passwordUpdatedAt":1755928332766,"providerUserInfo":[{"providerId":"password","email":"tech@ai-eva.com","federatedId":"tech@ai-eva.com","rawId":"tech@ai-eva.com","displayName":"管理者","photoUrl":""}],"validSince":"1755928332","email":"tech@ai-eva.com","emailVerified":false,"disabled":false},{"localId":"XQqymf2dN3Ygkx8aFe1MuadJ790m","createdAt":"1755842951741","lastLoginAt":"1755842951741","displayName":"伊藤 健","passwordHash":"fakeHash:salt=fakeSaltxCAOhmRq1pljL4vwAjnp:password=vq0VGBxp","salt":"fakeSaltxCAOhmRq1pljL4vwAjnp","passwordUpdatedAt":1755928332766,"providerUserInfo":[{"providerId":"password","email":"student065@example.com","federatedId":"student065@example.com","rawId":"student065@example.com","displayName":"伊藤 健"}],"validSince":"1755928332","email":"student065@example.com","emailVerified":false,"disabled":false},{"localId":"ZIM2RA0y7d51pOEXEOwZuBdLNY45","createdAt":"1755842951748","lastLoginAt":"1755842951748","displayName":"渡辺 彩香","passwordHash":"fakeHash:salt=fakeSaltX4Zkd11KuGvHQ3nn2xtY:password=IbDhqRYe","salt":"fakeSaltX4Zkd11KuGvHQ3nn2xtY","passwordUpdatedAt":1755928332766,"providerUserInfo":[{"providerId":"password","email":"student036@example.com","federatedId":"student036@example.com","rawId":"student036@example.com","displayName":"渡辺 彩香"}],"validSince":"1755928332","email":"student036@example.com","emailVerified":false,"disabled":false},{"localId":"ZRK5PRpsJKEHe0Fmt3bdNA23PTNG","createdAt":"1755842951675","lastLoginAt":"1755842951675","displayName":"中村 美咲","passwordHash":"fakeHash:salt=fakeSalt69HBuzWSi82VuxD5v4lz:password=9QFSiO0R","salt":"fakeSalt69HBuzWSi82VuxD5v4lz","passwordUpdatedAt":1755928332766,"providerUserInfo":[{"providerId":"password","email":"student008@example.com","federatedId":"student008@example.com","rawId":"student008@example.com","displayName":"中村 美咲"}],"validSince":"1755928332","email":"student008@example.com","emailVerified":false,"disabled":false},{"localId":"ZaCopFTTF4JHJVYNZoFZSe1kKgjZ","createdAt":"1755842951770","lastLoginAt":"1755842951770","displayName":"中村 美咲","passwordHash":"fakeHash:salt=fakeSaltDznLhq3VmboO0v5jq3Wb:password=k4gwmPXr","salt":"fakeSaltDznLhq3VmboO0v5jq3Wb","passwordUpdatedAt":1755928332766,"providerUserInfo":[{"providerId":"password","email":"student098@example.com","federatedId":"student098@example.com","rawId":"student098@example.com","displayName":"中村 美咲"}],"validSince":"1755928332","email":"student098@example.com","emailVerified":false,"disabled":false},{"localId":"ZjNhmMi1TE87FwBfHL7em2isZGoL","createdAt":"1755842951619","lastLoginAt":"1755842951619","displayName":"中村 美咲","passwordHash":"fakeHash:salt=fakeSaltnWcquutKUW6fCKu67cj4:password=906WIGoN","salt":"fakeSaltnWcquutKUW6fCKu67cj4","passwordUpdatedAt":1755928332766,"providerUserInfo":[{"providerId":"password","email":"student028@example.com","federatedId":"student028@example.com","rawId":"student028@example.com","displayName":"中村 美咲"}],"validSince":"1755928332","email":"student028@example.com","emailVerified":false,"disabled":false},{"localId":"a13yTc5TEVjI5V5Vo6jKDFmxcibe","createdAt":"1755842951690","lastLoginAt":"1755842951690","displayName":"伊藤 健","passwordHash":"fakeHash:salt=fakeSaltoCocawogg3hTgbIHPWD7:password=eRMKtsCT","salt":"fakeSaltoCocawogg3hTgbIHPWD7","passwordUpdatedAt":1755928332766,"providerUserInfo":[{"providerId":"password","email":"student055@example.com","federatedId":"student055@example.com","rawId":"student055@example.com","displayName":"伊藤 健"}],"validSince":"1755928332","email":"student055@example.com","emailVerified":false,"disabled":false},{"localId":"bJeiqXdt2eJulsQp8u4SX5Vj0bJS","createdAt":"1755842951766","lastLoginAt":"1755842951766","displayName":"加藤 結衣","passwordHash":"fakeHash:salt=fakeSaltpGRovvgOUdv2jAV2g8gG:password=pNsbvJvn","salt":"fakeSaltpGRovvgOUdv2jAV2g8gG","passwordUpdatedAt":1755928332766,"providerUserInfo":[{"providerId":"password","email":"student010@example.com","federatedId":"student010@example.com","rawId":"student010@example.com","displayName":"加藤 結衣"}],"validSince":"1755928332","email":"student010@example.com","emailVerified":false,"disabled":false},{"localId":"bdF9lpc27qkfYCa2kEd6sDnal5IA","createdAt":"1755842951673","lastLoginAt":"1755842951673","displayName":"加藤 結衣","passwordHash":"fakeHash:salt=fakeSalt8i1jPM6cXf9GVuS49GIl:password=DsJqp3Gt","salt":"fakeSalt8i1jPM6cXf9GVuS49GIl","passwordUpdatedAt":1755928332766,"providerUserInfo":[{"providerId":"password","email":"student060@example.com","federatedId":"student060@example.com","rawId":"student060@example.com","displayName":"加藤 結衣"}],"validSince":"1755928332","email":"student060@example.com","emailVerified":false,"disabled":false},{"localId":"ceh6Jw0y0yebCg3MD8q4KEcLPhBq","createdAt":"1755842951707","lastLoginAt":"1755842951707","displayName":"田中 一郎","passwordHash":"fakeHash:salt=fakeSaltyxNaGtPwLbqcgJNR8UDo:password=PMhFaSlK","salt":"fakeSaltyxNaGtPwLbqcgJNR8UDo","passwordUpdatedAt":1755928332766,"providerUserInfo":[{"providerId":"password","email":"student033@example.com","federatedId":"student033@example.com","rawId":"student033@example.com","displayName":"田中 一郎"}],"validSince":"1755928332","email":"student033@example.com","emailVerified":false,"disabled":false},{"localId":"chIzmWwHgFsAwizoQyKqi1p6dr1D","createdAt":"1755842951677","lastLoginAt":"1755842951677","displayName":"高橋 真美","passwordHash":"fakeHash:salt=fakeSaltUNSDHYMlB6HxAZsisXy6:password=FZdKKcpH","salt":"fakeSaltUNSDHYMlB6HxAZsisXy6","passwordUpdatedAt":1755928332766,"providerUserInfo":[{"providerId":"password","email":"student054@example.com","federatedId":"student054@example.com","rawId":"student054@example.com","displayName":"高橋 真美"}],"validSince":"1755928332","email":"student054@example.com","emailVerified":false,"disabled":false},{"localId":"ciRgAIBVmh2jiQQhemgcxgDjij1v","createdAt":"1755842951711","lastLoginAt":"1755842951711","displayName":"山本 翔","passwordHash":"fakeHash:salt=fakeSaltJ7zi88jQxGaw73TrRPqq:password=5L098aNQ","salt":"fakeSaltJ7zi88jQxGaw73TrRPqq","passwordUpdatedAt":1755928332766,"providerUserInfo":[{"providerId":"password","email":"student077@example.com","federatedId":"student077@example.com","rawId":"student077@example.com","displayName":"山本 翔"}],"validSince":"1755928332","email":"student077@example.com","emailVerified":false,"disabled":false},{"localId":"dXZt71fjp5riygdcIZ7xr6gMJbyQ","createdAt":"1755842951611","lastLoginAt":"1755842951611","displayName":"加藤 結衣","passwordHash":"fakeHash:salt=fakeSaltFgOKJAmDz0mYWVpKTfEb:password=MxRvyZeS","salt":"fakeSaltFgOKJAmDz0mYWVpKTfEb","passwordUpdatedAt":1755928332766,"providerUserInfo":[{"providerId":"password","email":"student070@example.com","federatedId":"student070@example.com","rawId":"student070@example.com","displayName":"加藤 結衣"}],"validSince":"1755928332","email":"student070@example.com","emailVerified":false,"disabled":false},{"localId":"dkUVtv5NbQGX4Pl9H5rWRdoR2hBd","createdAt":"1755842951756","lastLoginAt":"1755842951756","displayName":"中村 美咲","passwordHash":"fakeHash:salt=fakeSaltJtLLVjc14Fr9zvhYhDo1:password=uip0eh0u","salt":"fakeSaltJtLLVjc14Fr9zvhYhDo1","passwordUpdatedAt":1755928332766,"providerUserInfo":[{"providerId":"password","email":"student068@example.com","federatedId":"student068@example.com","rawId":"student068@example.com","displayName":"中村 美咲"}],"validSince":"1755928332","email":"student068@example.com","emailVerified":false,"disabled":false},{"localId":"eYUmmD3ARc8nF1kHtevC6YpmiUNk","createdAt":"1755842951773","lastLoginAt":"1755842951773","displayName":"田中 一郎","passwordHash":"fakeHash:salt=fakeSaltQW7vyzRmoqro871cXSeA:password=o5WVLpQn","salt":"fakeSaltQW7vyzRmoqro871cXSeA","passwordUpdatedAt":1755928332766,"providerUserInfo":[{"providerId":"password","email":"student023@example.com","federatedId":"student023@example.com","rawId":"student023@example.com","displayName":"田中 一郎"}],"validSince":"1755928332","email":"student023@example.com","emailVerified":false,"disabled":false},{"localId":"f8XyQB6FZJfQiJ37TqqHx9v0rOMK","createdAt":"1755842951745","lastLoginAt":"1755842951745","displayName":"鈴木 花子","passwordHash":"fakeHash:salt=fakeSalt5U6L88RFCAJJTzoV7vOx:password=P4pejCWB","salt":"fakeSalt5U6L88RFCAJJTzoV7vOx","passwordUpdatedAt":1755928332766,"providerUserInfo":[{"providerId":"password","email":"student042@example.com","federatedId":"student042@example.com","rawId":"student042@example.com","displayName":"鈴木 花子"}],"validSince":"1755928332","email":"student042@example.com","emailVerified":false,"disabled":false},{"localId":"fKeJ1Z1JqSQpIVu6KK8GfjVJ8qHu","createdAt":"1755842951624","lastLoginAt":"1755842951624","displayName":"伊藤 健","passwordHash":"fakeHash:salt=fakeSaltmkOkZadPjeqYJWstO0XM:password=7gRWx1YV","salt":"fakeSaltmkOkZadPjeqYJWstO0XM","passwordUpdatedAt":1755928332766,"providerUserInfo":[{"providerId":"password","email":"student095@example.com","federatedId":"student095@example.com","rawId":"student095@example.com","displayName":"伊藤 健"}],"validSince":"1755928332","email":"student095@example.com","emailVerified":false,"disabled":false},{"localId":"fnsZ7Fpwe0N5TYdLzSZ0wrlRkke6","createdAt":"1755842951668","lastLoginAt":"1755842951668","displayName":"渡辺 彩香","passwordHash":"fakeHash:salt=fakeSaltvWJogtMR8qnDvTwikeEa:password=pTXjtPKA","salt":"fakeSaltvWJogtMR8qnDvTwikeEa","passwordUpdatedAt":1755928332766,"providerUserInfo":[{"providerId":"password","email":"student086@example.com","federatedId":"student086@example.com","rawId":"student086@example.com","displayName":"渡辺 彩香"}],"validSince":"1755928332","email":"student086@example.com","emailVerified":false,"disabled":false},{"localId":"gPFhQ02j7GOehaglJKRxcrofB7u6","createdAt":"1755842951709","lastLoginAt":"1755842951709","displayName":"高橋 真美","passwordHash":"fakeHash:salt=fakeSaltMdtnpYOymlIH1ViG0crt:password=Aw2Snkqm","salt":"fakeSaltMdtnpYOymlIH1ViG0crt","passwordUpdatedAt":1755928332766,"providerUserInfo":[{"providerId":"password","email":"student044@example.com","federatedId":"student044@example.com","rawId":"student044@example.com","displayName":"高橋 真美"}],"validSince":"1755928332","email":"student044@example.com","emailVerified":false,"disabled":false},{"localId":"gRaTNMAU6lxTkFdA6AOh57Xw5jgs","createdAt":"1755842951536","lastLoginAt":"1755842951536","displayName":"高橋 真美","passwordHash":"fakeHash:salt=fakeSalthFKI9fHyoJ6dAUV0URWb:password=83DDEpvd","salt":"fakeSalthFKI9fHyoJ6dAUV0URWb","passwordUpdatedAt":1755928332766,"providerUserInfo":[{"providerId":"password","email":"student094@example.com","federatedId":"student094@example.com","rawId":"student094@example.com","displayName":"高橋 真美"}],"validSince":"1755928332","email":"student094@example.com","emailVerified":false,"disabled":false},{"localId":"gnlndRH16DeSgv72RenUVz38UcGm","createdAt":"1755842951763","lastLoginAt":"1755842951763","displayName":"高橋 真美","passwordHash":"fakeHash:salt=fakeSaltWHOdKv3tqStHtPechyUR:password=9xMejxBJ","salt":"fakeSaltWHOdKv3tqStHtPechyUR","passwordUpdatedAt":1755928332766,"providerUserInfo":[{"providerId":"password","email":"student064@example.com","federatedId":"student064@example.com","rawId":"student064@example.com","displayName":"高橋 真美"}],"validSince":"1755928332","email":"student064@example.com","emailVerified":false,"disabled":false},{"localId":"hJwhoDYB2n7rKHqFEKkpqdFe3guq","createdAt":"1755842951528","lastLoginAt":"1755842951528","displayName":"田中 一郎","passwordHash":"fakeHash:salt=fakeSaltMRxZFlRQ1AEvbteUo4Qi:password=wQvWk4qT","salt":"fakeSaltMRxZFlRQ1AEvbteUo4Qi","passwordUpdatedAt":1755928332767,"providerUserInfo":[{"providerId":"password","email":"student063@example.com","federatedId":"student063@example.com","rawId":"student063@example.com","displayName":"田中 一郎"}],"validSince":"1755928332","email":"student063@example.com","emailVerified":false,"disabled":false},{"localId":"hoyGl05b3AiaJCYNGfOYbG5V71vh","createdAt":"1755842951576","lastLoginAt":"1755842951576","displayName":"中村 美咲","passwordHash":"fakeHash:salt=fakeSaltDxYG4iBEpk9B6e7oicUY:password=A4F5LCmo","salt":"fakeSaltDxYG4iBEpk9B6e7oicUY","passwordUpdatedAt":1755928332767,"providerUserInfo":[{"providerId":"password","email":"student088@example.com","federatedId":"student088@example.com","rawId":"student088@example.com","displayName":"中村 美咲"}],"validSince":"1755928332","email":"student088@example.com","emailVerified":false,"disabled":false},{"localId":"i73tk0domZzUqK16o4nnrhdgeunP","createdAt":"1755590984704","lastLoginAt":"1755590984704","validSince":"1755928332","emailVerified":false,"disabled":false},{"localId":"iHwtdJw0i25uDJK3p2K7UiG7hxlB","createdAt":"1755842951626","lastLoginAt":"1755842951626","displayName":"田中 一郎","passwordHash":"fakeHash:salt=fakeSaltoQFfp1iqvAEVBYqAqdUs:password=f47ZGstb","salt":"fakeSaltoQFfp1iqvAEVBYqAqdUs","passwordUpdatedAt":1755928332767,"providerUserInfo":[{"providerId":"password","email":"student013@example.com","federatedId":"student013@example.com","rawId":"student013@example.com","displayName":"田中 一郎"}],"validSince":"1755928332","email":"student013@example.com","emailVerified":false,"disabled":false},{"localId":"iR8V82DwWZgo0uPHGHzbE83SNdPE","createdAt":"1755592481463","lastLoginAt":"1755592625788","displayName":"金谷","photoUrl":"","passwordHash":"fakeHash:salt=fakeSaltYSgdbgOhbVvyqoaIAWvc:password=19751975","salt":"fakeSaltYSgdbgOhbVvyqoaIAWvc","passwordUpdatedAt":1755928332767,"providerUserInfo":[{"providerId":"password","email":"ewige.liebe.yt@gmail.com","federatedId":"ewige.liebe.yt@gmail.com","rawId":"ewige.liebe.yt@gmail.com","displayName":"金谷","photoUrl":""}],"validSince":"1755928332","email":"ewige.liebe.yt@gmail.com","emailVerified":false,"disabled":false},{"localId":"ikm5qFzcjVCtRnvc7LSPNCWalUOs","createdAt":"1755842951743","lastLoginAt":"1755842951743","displayName":"加藤 結衣","passwordHash":"fakeHash:salt=fakeSalt1v6320hkuEk0cnwUuygd:password=8RKiiemt","salt":"fakeSalt1v6320hkuEk0cnwUuygd","passwordUpdatedAt":1755928332767,"providerUserInfo":[{"providerId":"password","email":"student040@example.com","federatedId":"student040@example.com","rawId":"student040@example.com","displayName":"加藤 結衣"}],"validSince":"1755928332","email":"student040@example.com","emailVerified":false,"disabled":false},{"localId":"iyGdWVT5ZAhAgQzoDGmMFqFXLTjh","createdAt":"1755842951564","lastLoginAt":"1755842951564","displayName":"山本 翔","passwordHash":"fakeHash:salt=fakeSaltsKhtqmYugReBFR3eNiHQ:password=3HLZMfZh","salt":"fakeSaltsKhtqmYugReBFR3eNiHQ","passwordUpdatedAt":1755928332767,"providerUserInfo":[{"providerId":"password","email":"student007@example.com","federatedId":"student007@example.com","rawId":"student007@example.com","displayName":"山本 翔"}],"validSince":"1755928332","email":"student007@example.com","emailVerified":false,"disabled":false},{"localId":"k1T7NY10B0gqbfiEi7O9htK8wLVV","createdAt":"1755842951684","lastLoginAt":"1755842951684","displayName":"中村 美咲","passwordHash":"fakeHash:salt=fakeSalt73lLwQdUYqzEl8XQhCAq:password=jmSJTEWN","salt":"fakeSalt73lLwQdUYqzEl8XQhCAq","passwordUpdatedAt":1755928332767,"providerUserInfo":[{"providerId":"password","email":"student048@example.com","federatedId":"student048@example.com","rawId":"student048@example.com","displayName":"中村 美咲"}],"validSince":"1755928332","email":"student048@example.com","emailVerified":false,"disabled":false},{"localId":"lKM7joxGSagLQQ3iIfnFTDMWKmCG","createdAt":"1755842951705","lastLoginAt":"1755842951705","displayName":"田中 一郎","passwordHash":"fakeHash:salt=fakeSalt2D2Xt0Y6c2gNvcdK8PfX:password=67io1MV8","salt":"fakeSalt2D2Xt0Y6c2gNvcdK8PfX","passwordUpdatedAt":1755928332767,"providerUserInfo":[{"providerId":"password","email":"student073@example.com","federatedId":"student073@example.com","rawId":"student073@example.com","displayName":"田中 一郎"}],"validSince":"1755928332","email":"student073@example.com","emailVerified":false,"disabled":false},{"localId":"lUmQAyYyobPd4pqvlrr7i0LshvEq","createdAt":"1755842951695","lastLoginAt":"1755842951695","displayName":"小林 大輔","passwordHash":"fakeHash:salt=fakeSalt9ymvsnJtMxpANsPn47Pz:password=Fokgd1I7","salt":"fakeSalt9ymvsnJtMxpANsPn47Pz","passwordUpdatedAt":1755928332767,"providerUserInfo":[{"providerId":"password","email":"student089@example.com","federatedId":"student089@example.com","rawId":"student089@example.com","displayName":"小林 大輔"}],"validSince":"1755928332","email":"student089@example.com","emailVerified":false,"disabled":false},{"localId":"lqvsvxngeWvVuen6dPl2QElBqItf","createdAt":"1755842951666","lastLoginAt":"1755842951666","displayName":"小林 大輔","passwordHash":"fakeHash:salt=fakeSaltm9BWrtPkUOuXhqKAFwc2:password=ZuGXYtzY","salt":"fakeSaltm9BWrtPkUOuXhqKAFwc2","passwordUpdatedAt":1755928332767,"providerUserInfo":[{"providerId":"password","email":"student039@example.com","federatedId":"student039@example.com","rawId":"student039@example.com","displayName":"小林 大輔"}],"validSince":"1755928332","email":"student039@example.com","emailVerified":false,"disabled":false},{"localId":"mNcf3XD28hhqCAOk1oNfNileviQ9","createdAt":"1755842951693","lastLoginAt":"1755842951693","displayName":"加藤 結衣","passwordHash":"fakeHash:salt=fakeSaltME8NblC9WAzZpH7aj8h1:password=W4nYcN1G","salt":"fakeSaltME8NblC9WAzZpH7aj8h1","passwordUpdatedAt":1755928332767,"providerUserInfo":[{"providerId":"password","email":"student100@example.com","federatedId":"student100@example.com","rawId":"student100@example.com","displayName":"加藤 結衣"}],"validSince":"1755928332","email":"student100@example.com","emailVerified":false,"disabled":false},{"localId":"n4BI8H8KkZBwyt5kK0GURLplq3Rt","createdAt":"1755842951692","lastLoginAt":"1755842951692","displayName":"高橋 真美","passwordHash":"fakeHash:salt=fakeSalt6LctXzUsH3b7ma9oAX9Q:password=ddbRPxqh","salt":"fakeSalt6LctXzUsH3b7ma9oAX9Q","passwordUpdatedAt":1755928332767,"providerUserInfo":[{"providerId":"password","email":"student004@example.com","federatedId":"student004@example.com","rawId":"student004@example.com","displayName":"高橋 真美"}],"validSince":"1755928332","email":"student004@example.com","emailVerified":false,"disabled":false},{"localId":"nedN74erRa9VkreoxWIfyelSLoBA","createdAt":"1755842951650","lastLoginAt":"1755842951650","displayName":"佐藤 太郎","passwordHash":"fakeHash:salt=fakeSaltd6ADaWEreKFiR5jHRkmA:password=cVaH3ppU","salt":"fakeSaltd6ADaWEreKFiR5jHRkmA","passwordUpdatedAt":1755928332767,"providerUserInfo":[{"providerId":"password","email":"student071@example.com","federatedId":"student071@example.com","rawId":"student071@example.com","displayName":"佐藤 太郎"}],"validSince":"1755928332","email":"student071@example.com","emailVerified":false,"disabled":false},{"localId":"o4XUlWKzfzmdOrHZvFvXc5LnzWAA","createdAt":"1755842951543","lastLoginAt":"1755842951543","displayName":"小林 大輔","passwordHash":"fakeHash:salt=fakeSalt5Vto5nR9UtvKsNDReFG8:password=xPnIZviR","salt":"fakeSalt5Vto5nR9UtvKsNDReFG8","passwordUpdatedAt":1755928332767,"providerUserInfo":[{"providerId":"password","email":"student049@example.com","federatedId":"student049@example.com","rawId":"student049@example.com","displayName":"小林 大輔"}],"validSince":"1755928332","email":"student049@example.com","emailVerified":false,"disabled":false},{"localId":"oAPwGFm0RcMXayi2RKpI60cFmTMR","createdAt":"1755842951686","lastLoginAt":"1755842951686","displayName":"山本 翔","passwordHash":"fakeHash:salt=fakeSalt5HER4iBvYa708d2pdOdV:password=O0DNv4We","salt":"fakeSalt5HER4iBvYa708d2pdOdV","passwordUpdatedAt":1755928332767,"providerUserInfo":[{"providerId":"password","email":"student067@example.com","federatedId":"student067@example.com","rawId":"student067@example.com","displayName":"山本 翔"}],"validSince":"1755928332","email":"student067@example.com","emailVerified":false,"disabled":false},{"localId":"ozmwhPblolaeF5rddN6ZUZSxAFNR","createdAt":"1755842951762","lastLoginAt":"1755842951762","displayName":"中村 美咲","passwordHash":"fakeHash:salt=fakeSaltDChvZi2eQ9cmCnZCZr28:password=XiKaXFCr","salt":"fakeSaltDChvZi2eQ9cmCnZCZr28","passwordUpdatedAt":1755928332767,"providerUserInfo":[{"providerId":"password","email":"student038@example.com","federatedId":"student038@example.com","rawId":"student038@example.com","displayName":"中村 美咲"}],"validSince":"1755928332","email":"student038@example.com","emailVerified":false,"disabled":false},{"localId":"p2cm8oGwZA3YfMiJ2kekR4RkXMyN","createdAt":"1755845720760","lastLoginAt":"1755845980789","displayName":"国立EduSupport高校 管理者","photoUrl":"","passwordHash":"fakeHash:salt=fakeSaltdH1D2y0zLVl0clgwOxkq:password=12345678","salt":"fakeSaltdH1D2y0zLVl0clgwOxkq","passwordUpdatedAt":1755928332767,"providerUserInfo":[{"providerId":"password","email":"edusupport@test.com","federatedId":"edusupport@test.com","rawId":"edusupport@test.com","displayName":"国立EduSupport高校 管理者","photoUrl":""}],"validSince":"1755928332","email":"edusupport@test.com","emailVerified":false,"disabled":false},{"localId":"pKeXqbrb7DpFMmsdJhjnvJNhTcBs","createdAt":"1755842951550","lastLoginAt":"1755842951550","displayName":"伊藤 健","passwordHash":"fakeHash:salt=fakeSalt1C4xRqD87S9wMJ5h51Vf:password=scOojZru","salt":"fakeSalt1C4xRqD87S9wMJ5h51Vf","passwordUpdatedAt":1755928332767,"providerUserInfo":[{"providerId":"password","email":"student045@example.com","federatedId":"student045@example.com","rawId":"student045@example.com","displayName":"伊藤 健"}],"validSince":"1755928332","email":"student045@example.com","emailVerified":false,"disabled":false},{"localId":"pXIag5Z0WdR12lLkKj3DT47jFLAN","createdAt":"1755842951704","lastLoginAt":"1755842951704","displayName":"加藤 結衣","passwordHash":"fakeHash:salt=fakeSaltQtoRO2RN1FF4L67ShwOQ:password=dVemjmk7","salt":"fakeSaltQtoRO2RN1FF4L67ShwOQ","passwordUpdatedAt":1755928332767,"providerUserInfo":[{"providerId":"password","email":"student080@example.com","federatedId":"student080@example.com","rawId":"student080@example.com","displayName":"加藤 結衣"}],"validSince":"1755928332","email":"student080@example.com","emailVerified":false,"disabled":false},{"localId":"q5YiKPBaHkk5Xd75VuIhTAoQglZa","createdAt":"1755842951670","lastLoginAt":"1755842951670","displayName":"鈴木 花子","passwordHash":"fakeHash:salt=fakeSaltokfr2q2rTGvFfqNaRG2X:password=4B3IZUWu","salt":"fakeSaltokfr2q2rTGvFfqNaRG2X","passwordUpdatedAt":1755928332767,"providerUserInfo":[{"providerId":"password","email":"student062@example.com","federatedId":"student062@example.com","rawId":"student062@example.com","displayName":"鈴木 花子"}],"validSince":"1755928332","email":"student062@example.com","emailVerified":false,"disabled":false},{"localId":"qXUM3gFovKsr0glrs41v8GP0yvdm","createdAt":"1755842951655","lastLoginAt":"1755842951655","displayName":"鈴木 花子","passwordHash":"fakeHash:salt=fakeSaltWu2zkhMhDPuwT8hhVjjp:password=uYJPEdax","salt":"fakeSaltWu2zkhMhDPuwT8hhVjjp","passwordUpdatedAt":1755928332767,"providerUserInfo":[{"providerId":"password","email":"student022@example.com","federatedId":"student022@example.com","rawId":"student022@example.com","displayName":"鈴木 花子"}],"validSince":"1755928332","email":"student022@example.com","emailVerified":false,"disabled":false},{"localId":"qscFoqVEpYVeRuCxiRrljEZ2H7nJ","createdAt":"1755842951768","lastLoginAt":"1755842951768","displayName":"佐藤 太郎","passwordHash":"fakeHash:salt=fakeSaltZa8jVO2GeJwjpS6DQMIB:password=nt1GTZ20","salt":"fakeSaltZa8jVO2GeJwjpS6DQMIB","passwordUpdatedAt":1755928332767,"providerUserInfo":[{"providerId":"password","email":"student081@example.com","federatedId":"student081@example.com","rawId":"student081@example.com","displayName":"佐藤 太郎"}],"validSince":"1755928332","email":"student081@example.com","emailVerified":false,"disabled":false},{"localId":"rYwOhE9WTBIPHRobK2nMc0BJN7K1","createdAt":"1755842951622","lastLoginAt":"1755842951622","displayName":"渡辺 彩香","passwordHash":"fakeHash:salt=fakeSaltAyEvxrsUwVEcoIPmxbfL:password=ijSzuIQg","salt":"fakeSaltAyEvxrsUwVEcoIPmxbfL","passwordUpdatedAt":1755928332767,"providerUserInfo":[{"providerId":"password","email":"student076@example.com","federatedId":"student076@example.com","rawId":"student076@example.com","displayName":"渡辺 彩香"}],"validSince":"1755928332","email":"student076@example.com","emailVerified":false,"disabled":false},{"localId":"syi4roNTivyo0q7avISFgkBG9aq8","createdAt":"1755842951776","lastLoginAt":"1755842951776","displayName":"佐藤 太郎","passwordHash":"fakeHash:salt=fakeSaltv2dSNcKqeXBweJj7Xd99:password=0hrXav4W","salt":"fakeSaltv2dSNcKqeXBweJj7Xd99","passwordUpdatedAt":1755928332767,"providerUserInfo":[{"providerId":"password","email":"student021@example.com","federatedId":"student021@example.com","rawId":"student021@example.com","displayName":"佐藤 太郎"}],"validSince":"1755928332","email":"student021@example.com","emailVerified":false,"disabled":false},{"localId":"tOy1sdDf1xzvh9KHvJOfP1QiBiHO","createdAt":"1755592112407","lastLoginAt":"1755592112407","displayName":"テスト　太郎","validSince":"1755928332","email":"taro@exmaple.com","emailVerified":false,"disabled":false},{"localId":"tdZ6tWQjT9Vy01kTcMbDDMRCocsh","createdAt":"1755842951580","lastLoginAt":"1755842951580","displayName":"山本 翔","passwordHash":"fakeHash:salt=fakeSaltuTZdbFk5cI3HdwFTerZi:password=vtTj1Szh","salt":"fakeSaltuTZdbFk5cI3HdwFTerZi","passwordUpdatedAt":1755928332767,"providerUserInfo":[{"providerId":"password","email":"student047@example.com","federatedId":"student047@example.com","rawId":"student047@example.com","displayName":"山本 翔"}],"validSince":"1755928332","email":"student047@example.com","emailVerified":false,"disabled":false},{"localId":"uDrdeBaPXeVuOtvjVEpBtjgy85Lk","createdAt":"1755842951702","lastLoginAt":"1755842951702","displayName":"中村 美咲","passwordHash":"fakeHash:salt=fakeSaltQ92JAO5b0kc7Ag0GVn4y:password=6LjIWhP5","salt":"fakeSaltQ92JAO5b0kc7Ag0GVn4y","passwordUpdatedAt":1755928332767,"providerUserInfo":[{"providerId":"password","email":"student058@example.com","federatedId":"student058@example.com","rawId":"student058@example.com","displayName":"中村 美咲"}],"validSince":"1755928332","email":"student058@example.com","emailVerified":false,"disabled":false},{"localId":"uMwu65R0wNx7gltKgk5nTDGO8OI5","createdAt":"1755842951547","lastLoginAt":"1755842951547","displayName":"小林 大輔","passwordHash":"fakeHash:salt=fakeSaltALYcmy5D8JJxDKqLCrvc:password=zROg9t16","salt":"fakeSaltALYcmy5D8JJxDKqLCrvc","passwordUpdatedAt":1755928332767,"providerUserInfo":[{"providerId":"password","email":"student029@example.com","federatedId":"student029@example.com","rawId":"student029@example.com","displayName":"小林 大輔"}],"validSince":"1755928332","email":"student029@example.com","emailVerified":false,"disabled":false},{"localId":"uhvQ9M4pvRYuO3npH5aZZWtc1hfg","createdAt":"1755842951525","lastLoginAt":"1755842951525","displayName":"小林 大輔","passwordHash":"fakeHash:salt=fakeSaltZ40WFR1IXFYQf0IyO32Y:password=2g5esybF","salt":"fakeSaltZ40WFR1IXFYQf0IyO32Y","passwordUpdatedAt":1755928332767,"providerUserInfo":[{"providerId":"password","email":"student059@example.com","federatedId":"student059@example.com","rawId":"student059@example.com","displayName":"小林 大輔"}],"validSince":"1755928332","email":"student059@example.com","emailVerified":false,"disabled":false},{"localId":"v8kUdMlUj1Z5cTzYMRorBYMy6UKS","createdAt":"1755842951753","lastLoginAt":"1755842951753","displayName":"佐藤 太郎","passwordHash":"fakeHash:salt=fakeSaltsJFurEpC1wZ6nJGdVAaZ:password=1Su6iWs1","salt":"fakeSaltsJFurEpC1wZ6nJGdVAaZ","passwordUpdatedAt":1755928332767,"providerUserInfo":[{"providerId":"password","email":"student051@example.com","federatedId":"student051@example.com","rawId":"student051@example.com","displayName":"佐藤 太郎"}],"validSince":"1755928332","email":"student051@example.com","emailVerified":false,"disabled":false},{"localId":"vFLwn8v8RNhLZlUdvLCQQePRxQ0m","createdAt":"1755842951573","lastLoginAt":"1755842951573","displayName":"高橋 真美","passwordHash":"fakeHash:salt=fakeSaltJvCL2VCvwuMgmGCVQHMp:password=RzXcTNxZ","salt":"fakeSaltJvCL2VCvwuMgmGCVQHMp","passwordUpdatedAt":1755928332767,"providerUserInfo":[{"providerId":"password","email":"student084@example.com","federatedId":"student084@example.com","rawId":"student084@example.com","displayName":"高橋 真美"}],"validSince":"1755928332","email":"student084@example.com","emailVerified":false,"disabled":false},{"localId":"vWtZJM2PK5iAyeYwsEGViKXtyMvO","createdAt":"1755842951740","lastLoginAt":"1755842951740","displayName":"鈴木 花子","passwordHash":"fakeHash:salt=fakeSaltrfFlonRmPgHoal7e0h89:password=Fy4AoKc4","salt":"fakeSaltrfFlonRmPgHoal7e0h89","passwordUpdatedAt":1755928332767,"providerUserInfo":[{"providerId":"password","email":"student012@example.com","federatedId":"student012@example.com","rawId":"student012@example.com","displayName":"鈴木 花子"}],"validSince":"1755928332","email":"student012@example.com","emailVerified":false,"disabled":false},{"localId":"wgh5OK2EEEqWwT3JY1YrkpvTcNP7","createdAt":"1755842951613","lastLoginAt":"1755842951613","displayName":"高橋 真美","passwordHash":"fakeHash:salt=fakeSaltDl0rt1Ycjn7EJNNgHzwm:password=m6h8CXC6","salt":"fakeSaltDl0rt1Ycjn7EJNNgHzwm","passwordUpdatedAt":1755928332767,"providerUserInfo":[{"providerId":"password","email":"student034@example.com","federatedId":"student034@example.com","rawId":"student034@example.com","displayName":"高橋 真美"}],"validSince":"1755928332","email":"student034@example.com","emailVerified":false,"disabled":false},{"localId":"wtu6M6bZpQASozcoyUVXVqxgpL27","createdAt":"1755846001457","lastLoginAt":"1755846001457","displayName":"金谷 拓","validSince":"1755928332","email":"kanaya@teacher.com","emailVerified":false,"disabled":false},{"localId":"xAfPmGWO87cs6k7pavTP0DUeD8sm","createdAt":"1755842951733","lastLoginAt":"1755842951733","displayName":"渡辺 彩香","passwordHash":"fakeHash:salt=fakeSalts9gDcLUuYvhN2USsKhce:password=Y3HduEKm","salt":"fakeSalts9gDcLUuYvhN2USsKhce","passwordUpdatedAt":1755928332767,"providerUserInfo":[{"providerId":"password","email":"student046@example.com","federatedId":"student046@example.com","rawId":"student046@example.com","displayName":"渡辺 彩香"}],"validSince":"1755928332","email":"student046@example.com","emailVerified":false,"disabled":false},{"localId":"xgio7ZkG8V9zwVW4XRP2uA8h4vhO","createdAt":"1755842951687","lastLoginAt":"1755842951687","displayName":"小林 大輔","passwordHash":"fakeHash:salt=fakeSaltEiAGZTYjJV1IZSjrpOOf:password=hUhQsAnh","salt":"fakeSaltEiAGZTYjJV1IZSjrpOOf","passwordUpdatedAt":1755928332767,"providerUserInfo":[{"providerId":"password","email":"student069@example.com","federatedId":"student069@example.com","rawId":"student069@example.com","displayName":"小林 大輔"}],"validSince":"1755928332","email":"student069@example.com","emailVerified":false,"disabled":false},{"localId":"yWZ0FsXOM4rfEgjf5B74X0wRjRQO","createdAt":"1755842951600","lastLoginAt":"1755842951600","displayName":"鈴木 花子","passwordHash":"fakeHash:salt=fakeSaltaTXmGA8ZsNJm66HH1vzP:password=eNFPtZ2n","salt":"fakeSaltaTXmGA8ZsNJm66HH1vzP","passwordUpdatedAt":1755928332767,"providerUserInfo":[{"providerId":"password","email":"student032@example.com","federatedId":"student032@example.com","rawId":"student032@example.com","displayName":"鈴木 花子"}],"validSince":"1755928332","email":"student032@example.com","emailVerified":false,"disabled":false},{"localId":"zGWB5ySnxcjqP1FbK3wRZewpvCiD","createdAt":"1755773061141","lastLoginAt":"1755773061141","displayName":"テスト　太郎","passwordHash":"fakeHash:salt=fakeSaltrGNAWu4QA8Y1wjLFXD6j:password=4u15s5yW","salt":"fakeSaltrGNAWu4QA8Y1wjLFXD6j","passwordUpdatedAt":1755928332767,"providerUserInfo":[{"providerId":"password","email":"testtaro@exmaple.com","federatedId":"testtaro@exmaple.com","rawId":"testtaro@exmaple.com","displayName":"テスト　太郎"}],"validSince":"1755928332","email":"testtaro@exmaple.com","emailVerified":false,"disabled":false},{"localId":"zPLfjW4PgoMUf4HUOiryw24TTEG6","createdAt":"1755842951643","lastLoginAt":"1755842951643","displayName":"田中 一郎","passwordHash":"fakeHash:salt=fakeSalt7QUfg4uYPDbnh9uFHW0Q:password=4hewBuSr","salt":"fakeSalt7QUfg4uYPDbnh9uFHW0Q","passwordUpdatedAt":1755928332767,"providerUserInfo":[{"providerId":"password","email":"student003@example.com","federatedId":"student003@example.com","rawId":"student003@example.com","displayName":"田中 一郎"}],"validSince":"1755928332","email":"student003@example.com","emailVerified":false,"disabled":false},{"localId":"zYCWSXb83yc5QKDzD2LpzSgWdxMM","createdAt":"1755842951559","lastLoginAt":"1755842951559","displayName":"伊藤 健","passwordHash":"fakeHash:salt=fakeSaltapw1MZI9LiNkz0C7RnJQ:password=JfB2PiVi","salt":"fakeSaltapw1MZI9LiNkz0C7RnJQ","passwordUpdatedAt":1755928332767,"providerUserInfo":[{"providerId":"password","email":"student035@example.com","federatedId":"student035@example.com","rawId":"student035@example.com","displayName":"伊藤 健"}],"validSince":"1755928332","email":"student035@example.com","emailVerified":false,"disabled":false},{"localId":"zwuRCU3aaWHzHkTcxImg9fjVrAZ6","createdAt":"1755842951760","lastLoginAt":"1755842951760","displayName":"伊藤 健","passwordHash":"fakeHash:salt=fakeSaltRHVmCRSxieSnnVcDUTqG:password=LI9Jve4l","salt":"fakeSaltRHVmCRSxieSnnVcDUTqG","passwordUpdatedAt":1755928332767,"providerUserInfo":[{"providerId":"password","email":"student085@example.com","federatedId":"student085@example.com","rawId":"student085@example.com","displayName":"伊藤 健"}],"validSince":"1755928332","email":"student085@example.com","emailVerified":false,"disabled":false}]}